epdlib/Block.py
epdlib/Layout.py
epdlib/Screen.py
epdlib/__init__.py
epdlib/constants.py
epdlib/version.py
epdlib-0.6.5.2.dist-info/LICENSE
epdlib-0.6.5.2.dist-info/METADATA
epdlib-0.6.5.2.dist-info/WHEEL
epdlib-0.6.5.2.dist-info/top_level.txt
epdlib-0.6.5.2.dist-info/RECORD
