Metadata-Version: 2.1
Name: epdlib
Version: 0.6.5.2
Summary: library for creating dynamic layouts for frame-buffered devices
Home-page: https://github.com/txoof/epdlib
Author: Aaron ciuffo
Author-email: aaron.ciuffo@gmail.com
Project-URL: Source, https://github.com/txoof/epdlib
Keywords: graphics e-paper display waveshare
Classifier: Intended Audience :: Developers
Classifier: Topic :: Software Development :: Libraries :: Python Modules
Classifier: Programming Language :: Python :: 3.7
Classifier: License :: OSI Approved :: GNU General Public License v3 or later (GPLv3+)
Classifier: Operating System :: OS Independent
Requires-Python: >=3.7
License-File: LICENSE
Requires-Dist: Pillow
Requires-Dist: spidev
Requires-Dist: RPi.GPIO
Requires-Dist: gpiozero
Requires-Dist: lgpio
